{
  "repository": "https://github.com/nandanadileep/neural-networks-implementation.git",
  "code_metrics": {
    "LOC": 0,
    "TODOs_FIXME_HACK": 0,
    "AvgCyclomaticComplexity": 0,
    "DebtScore": 0.0,
    "TotalFunctions": 0,
    "MaxComplexity": 0,
    "MinComplexity": 0,
    "FilesAnalyzed": 0,
    "ComplexityDistribution": {
      "low": 0,
      "medium": 0,
      "high": 0,
      "very_high": 0
    }
  },
  "dependency_metrics": {
    "total_files": 0,
    "total_functions": 0,
    "total_classes": 0,
    "total_external_dependencies": 0,
    "total_edges": 0,
    "average_connections_per_node": 0,
    "most_dependent_files": [],
    "most_depended_on_files": [],
    "circular_dependencies": 0,
    "circular_dependency_chains": [],
    "graph_density": 0,
    "graph_json": {
      "directed": true,
      "multigraph": false,
      "graph": {},
      "nodes": [],
      "links": []
    }
  },
  "duplication_metrics": {
    "files_analyzed": 0,
    "duplicate_pairs_found": 0,
    "similarity_threshold": 0.85,
    "shingle_size_k": 5,
    "duplicates": []
  },
  "analysis_method": "Tree-sitter AST + NetworkX + MinHash (Async - Local Storage)",
  "excluded_third_party": true,
  "excluded_tests": true,
  "analysis_errors": []
}